ckanext_issues-1.0.0-py3.8-nspkg.pth
ckanext/issues/auth.py
ckanext/issues/exception.py
ckanext/issues/plugin.py
ckanext/issues/assets/css/style.css
ckanext/issues/assets/js/autocomplete-action-api.js
ckanext/issues/assets/public/css/style.css
ckanext/issues/i18n/mk/LC_MESSAGES/ckanext-issues.mo
ckanext/issues/i18n/sq/LC_MESSAGES/ckanext-issues.mo
ckanext/issues/lib/__init__.py
ckanext/issues/lib/helpers.py
ckanext/issues/lib/util.py
ckanext/issues/logic/__init__.py
ckanext/issues/logic/action/__init__.py
ckanext/issues/logic/action/action.py
ckanext/issues/logic/schema/__init__.py
ckanext/issues/logic/schema/schema.py
ckanext/issues/logic/validators/__init__.py
ckanext/issues/logic/validators/validators.py
ckanext/issues/model/__init__.py
ckanext/issues/model/report.py
ckanext/issues/templates/issues/add.html
ckanext/issues/templates/issues/all_issues.html
ckanext/issues/templates/issues/base.html
ckanext/issues/templates/issues/base_form_page.html
ckanext/issues/templates/issues/comment_moderation.html
ckanext/issues/templates/issues/common.html
ckanext/issues/templates/issues/confirm_delete.html
ckanext/issues/templates/issues/dataset.html
ckanext/issues/templates/issues/edit.html
ckanext/issues/templates/issues/moderation.html
ckanext/issues/templates/issues/organization_issues.html
ckanext/issues/templates/issues/show.html
ckanext/issues/templates/issues/email/new_comment.html
ckanext/issues/templates/issues/email/new_issue.html
ckanext/issues/templates/package/read_base.html
ckanext/issues/templates/snippets/search_form.html
ckanext/issues/templates/snippets/search_result_text.html
ckanext/issues/tests/__init__.py
ckanext/issues/tests/factories.py
ckanext/issues/tests/fixtures.py
ckanext/issues/tests/logic/__init__.py
ckanext/issues/tests/logic/test_api.py
ckanext/issues/tests/logic/test_auth.py
ckanext/issues/tests/logic/test_validators.py
ckanext/issues/tests/logic/action/__init__.py
ckanext/issues/tests/logic/action/test_issue.py
ckanext_issues-1.0.0.dist-info/LICENSE
ckanext_issues-1.0.0.dist-info/METADATA
ckanext_issues-1.0.0.dist-info/NOTICE
ckanext_issues-1.0.0.dist-info/WHEEL
ckanext_issues-1.0.0.dist-info/entry_points.txt
ckanext_issues-1.0.0.dist-info/namespace_packages.txt
ckanext_issues-1.0.0.dist-info/top_level.txt
ckanext_issues-1.0.0.dist-info/RECORD
