Metadata-Version: 2.1
Name: ckanext-issues
Version: 1.0.0
Summary: CKAN Extension providing Issues (Task/Todos/...)
Home-page: https://github.com/keitaroinc/ckanext-issues
Author: Keitaro Inc
Author-email: info@keitaro.com
License: MIT
Keywords: CKAN ckanext issues
Platform: UNKNOWN
Classifier: Development Status :: 5 - Production/Stable
Classifier: License :: OSI Approved :: MIT License
Classifier: Programming Language :: Python :: 3 :: Only
Classifier: Programming Language :: Python :: 3.8
License-File: LICENSE
License-File: NOTICE
Requires-Dist: enum34
